deeploy/__init__.py
deeploy/_version.py
deeploy/client.py
deeploy/cli/__init__.py
deeploy/cli/deeploycli.py
deeploy/cli/interface.py
deeploy/cli/utils.py
deeploy/cli/custom_instances/__init__.py
deeploy/cli/custom_instances/explainer.py
deeploy/cli/custom_instances/model.py
deeploy/cli/custom_instances/model_repository.py
deeploy/cli/custom_instances/transformer.py
deeploy/cli/deploy_instances/__init__.py
deeploy/cli/deploy_instances/deeploy_explainer.py
deeploy/cli/deploy_instances/deeploy_model.py
deeploy/cli/deploy_instances/deeploy_transformer.py
deeploy/cli/parsers/__init__.py
deeploy/cli/parsers/parser_explainer.py
deeploy/cli/parsers/parser_model.py
deeploy/cli/parsers/parser_transformer.py
deeploy/cli/templates/README.md.j2
deeploy/cli/templates/__init__.py
deeploy/cli/templates/build.sh.j2
deeploy/cli/templates/metadata.json.j2
deeploy/cli/templates/reference.json.j2
deeploy/cli/templates/explainer/Dockerfile.j2
deeploy/cli/templates/explainer/__init__.py
deeploy/cli/templates/explainer/__main__.py.j2
deeploy/cli/templates/explainer/explainer.dill
deeploy/cli/templates/explainer/requirements.txt.j2
deeploy/cli/templates/explainer/sample_explainer.py.j2
deeploy/cli/templates/model/Dockerfile.j2
deeploy/cli/templates/model/__init__.py
deeploy/cli/templates/model/__main__.py.j2
deeploy/cli/templates/model/metadata.json.j2
deeploy/cli/templates/model/model.bst
deeploy/cli/templates/model/requirements.txt.j2
deeploy/cli/templates/model/sample_model.py.j2
deeploy/cli/templates/transformer/Dockerfile.j2
deeploy/cli/templates/transformer/__init__.py
deeploy/cli/templates/transformer/__main__.py.j2
deeploy/cli/templates/transformer/requirements.txt.j2
deeploy/cli/templates/transformer/sample_transformer.py.j2
deeploy/cli/wrappers/__init__.py
deeploy/cli/wrappers/explainer_wrapper.py
deeploy/cli/wrappers/model_wrapper.py
deeploy/cli/wrappers/transformer_wrapper.py
deeploy/common/__init__.py
deeploy/common/constants/__init__.py
deeploy/common/constants/pytorch.py
deeploy-1.54.1.dist-info/licenses/LICENSE
deeploy-1.54.1.dist-info/METADATA
deeploy-1.54.1.dist-info/WHEEL
deeploy-1.54.1.dist-info/entry_points.txt
deeploy-1.54.1.dist-info/top_level.txt
deeploy-1.54.1.dist-info/RECORD
